{
  "data": [
    {
      "id": 44991,
      "title": "Туннельное зрение",
      "kp_id": null,
      "imdb_id": "tt12600074",
      "world_art_id": null,
      "type": "movie",
      "add": "2020-11-03 12:14:02",
      "orig_title": "Tunnelblick",
      "year": "2019-01-01",
      "translations": [
        "Любительский (многоголосый закадровый) (@MUZOBOZ@)"
      ],
      "quality": "webdl",
      "translation": "Любительский (многоголосый закадровый) (@MUZOBOZ@)",
      "update": "2020-11-03 16:58:12",
      "iframe_src": ""
    },
    {
      "id": 44987,
      "title": "Дети райка",
      "kp_id": "8442",
      "imdb_id": "tt0037674",
      "world_art_id": null,
      "type": "movie",
      "add": "2020-11-03 08:01:58",
      "orig_title": "Les enfants du paradis",
      "year": "1945-03-09",
      "translations": [
        "Профессиональный (многоголосый закадровый) (Культура)"
      ],
      "quality": "bd",
      "translation": "Профессиональный (многоголосый закадровый) (Культура)",
      "update": "2020-11-03 16:02:25",
      "iframe_src": ""
    },
    {
      "id": 44805,
      "title": "Про паучка, с которым никто не дружил",
      "kp_id": "648067",
      "imdb_id": null,
      "world_art_id": null,
      "type": "movie",
      "add": "2020-10-26 17:45:39",
      "orig_title": "Про паучка, с которым никто не дружил",
      "year": "1975-01-01",
      "translations": [
        "Оригинальная дорожка"
      ],
      "quality": "dvdrip",
      "translation": "Оригинальная дорожка",
      "update": "2020-11-03 13:13:23",
      "iframe_src": ""
    },
    {
      "id": 44804,
      "title": "Почему куры денег не клюют",
      "kp_id": "469244",
      "imdb_id": "tt6024504",
      "world_art_id": null,
      "type": "movie",
      "add": "2020-10-26 17:41:50",
      "orig_title": "Pochemu deneg kury ne klyuyut",
      "year": "1990-01-01",
      "translations": [
        "Оригинальная дорожка"
      ],
      "quality": "dvdrip",
      "translation": "Оригинальная дорожка",
      "update": "2020-11-03 13:11:55",
      "iframe_src": ""
    },
    {
      "id": 44802,
      "title": "По следам Бамбра",
      "kp_id": "259948",
      "imdb_id": "tt6024374",
      "world_art_id": null,
      "type": "movie",
      "add": "2020-10-26 17:39:43",
      "orig_title": "Po sledam Bambra",
      "year": "1990-01-01",
      "translations": [
        "Оригинальная дорожка"
      ],
      "quality": "dvdrip",
      "translation": "Оригинальная дорожка",
      "update": "2020-11-03 13:11:09",
      "iframe_src": ""
    },
    {
      "id": 44801,
      "title": "Пирог со смеяникой",
      "kp_id": "581112",
      "imdb_id": null,
      "world_art_id": null,
      "type": "movie",
      "add": "2020-10-26 17:37:44",
      "orig_title": "Пирог со смеяникой",
      "year": "1980-01-01",
      "translations": [
        "Оригинальная дорожка"
      ],
      "quality": "dvdrip",
      "translation": "Оригинальная дорожка",
      "update": "2020-11-03 13:09:44",
      "iframe_src": ""
    },
    {
      "id": 44800,
      "title": "По щучьему велению",
      "kp_id": "818867",
      "imdb_id": "tt7003936",
      "world_art_id": null,
      "type": "movie",
      "add": "2020-10-26 17:33:50",
      "orig_title": "Po shchuchemu veleniyu",
      "year": "1970-01-01",
      "translations": [
        "Оригинальная дорожка"
      ],
      "quality": "dvdrip",
      "translation": "Оригинальная дорожка",
      "update": "2020-11-03 13:09:13",
      "iframe_src": ""
    },
    {
      "id": 44798,
      "title": "Петькины трюки",
      "kp_id": "591803",
      "imdb_id": null,
      "world_art_id": null,
      "type": "movie",
      "add": "2020-10-26 17:24:03",
      "orig_title": "Петькины трюки",
      "year": "1980-01-01",
      "translations": [
        "Оригинальная дорожка"
      ],
      "quality": "dvdrip",
      "translation": "Оригинальная дорожка",
      "update": "2020-11-03 13:08:10",
      "iframe_src": ""
    },
    {
      "id": 44795,
      "title": "Первая скрипка",
      "kp_id": "460461",
      "imdb_id": "tt6235230",
      "world_art_id": null,
      "type": "movie",
      "add": "2020-10-26 17:18:06",
      "orig_title": "Pervaya skripka",
      "year": "1958-01-01",
      "translations": [
        "Оригинальная дорожка"
      ],
      "quality": "dvdrip",
      "translation": "Оригинальная дорожка",
      "update": "2020-11-03 13:07:03",
      "iframe_src": ""
    },
    {
      "id": 44770,
      "title": "Папа, мама и золотая рыбка",
      "kp_id": "574070",
      "imdb_id": null,
      "world_art_id": null,
      "type": "movie",
      "add": "2020-10-25 19:01:58",
      "orig_title": "Папа, мама и золотая рыбка",
      "year": "1976-01-01",
      "translations": [
        "Оригинальная дорожка"
      ],
      "quality": "dvdrip",
      "translation": "Оригинальная дорожка",
      "update": "2020-11-03 13:06:23",
      "iframe_src": ""
    },
    {
      "id": 44769,
      "title": "Орел и крот",
      "kp_id": "630183",
      "imdb_id": "tt7479860",
      "world_art_id": null,
      "type": "movie",
      "add": "2020-10-25 18:55:00",
      "orig_title": "Oryol i krot",
      "year": "1944-01-01",
      "translations": [
        "Оригинальная дорожка"
      ],
      "quality": "sat",
      "translation": "Оригинальная дорожка",
      "update": "2020-11-03 13:05:32",
      "iframe_src": ""
    },
    {
      "id": 44768,
      "title": "Одуванчик — толстые щеки",
      "kp_id": "490210",
      "imdb_id": "tt5495286",
      "world_art_id": null,
      "type": "movie",
      "add": "2020-10-25 18:52:37",
      "orig_title": "Oduvanchik: tolstye scheki",
      "year": "1971-01-01",
      "translations": [
        "Оригинальная дорожка"
      ],
      "quality": "dvdrip",
      "translation": "Оригинальная дорожка",
      "update": "2020-11-03 13:04:42",
      "iframe_src": ""
    },
    {
      "id": 44767,
      "title": "Одуванчик",
      "kp_id": "629594",
      "imdb_id": null,
      "world_art_id": null,
      "type": "movie",
      "add": "2020-10-25 18:46:07",
      "orig_title": "Одуванчик",
      "year": "1975-01-01",
      "translations": [
        "Оригинальная дорожка"
      ],
      "quality": "dvdrip",
      "translation": "Оригинальная дорожка",
      "update": "2020-11-03 13:03:48",
      "iframe_src": ""
    },
    {
      "id": 44766,
      "title": "Одна лошадка белая",
      "kp_id": "625326",
      "imdb_id": "tt4584954",
      "world_art_id": null,
      "type": "movie",
      "add": "2020-10-25 18:40:40",
      "orig_title": "Odna loshadka belaya",
      "year": "1977-01-01",
      "translations": [
        "Оригинальная дорожка"
      ],
      "quality": "dvdrip",
      "translation": "Оригинальная дорожка",
      "update": "2020-11-03 13:03:10",
      "iframe_src": ""
    },
    {
      "id": 44765,
      "title": "Неудачники",
      "kp_id": "1000018",
      "imdb_id": "tt6011928",
      "world_art_id": null,
      "type": "movie",
      "add": "2020-10-25 18:38:04",
      "orig_title": "Neudachniki",
      "year": "1983-01-01",
      "translations": [
        "Оригинальная дорожка"
      ],
      "quality": "sat",
      "translation": "Оригинальная дорожка",
      "update": "2020-11-03 13:01:42",
      "iframe_src": ""
    },
    {
      "id": 44764,
      "title": "Как воробей ум искал",
      "kp_id": "594871",
      "imdb_id": "tt6011920",
      "world_art_id": null,
      "type": "movie",
      "add": "2020-10-25 18:35:51",
      "orig_title": "Kak vorobey um iskal",
      "year": "1970-01-01",
      "translations": [
        "Оригинальная дорожка"
      ],
      "quality": "dvdrip",
      "translation": "Оригинальная дорожка",
      "update": "2020-11-03 13:00:28",
      "iframe_src": ""
    },
    {
      "id": 44763,
      "title": "Мой зеленый крокодил",
      "kp_id": "257954",
      "imdb_id": "tt0480434",
      "world_art_id": null,
      "type": "movie",
      "add": "2020-10-25 18:33:40",
      "orig_title": "Moy zelenyy krokodil",
      "year": "1966-04-14",
      "translations": [
        "Оригинальная дорожка"
      ],
      "quality": "dvdrip",
      "translation": "Оригинальная дорожка",
      "update": "2020-11-03 12:59:15",
      "iframe_src": ""
    },
    {
      "id": 44762,
      "title": "Мой приятель светофор",
      "kp_id": "541902",
      "imdb_id": null,
      "world_art_id": null,
      "type": "movie",
      "add": "2020-10-25 18:31:40",
      "orig_title": "Мой приятель светофор",
      "year": "1978-01-01",
      "translations": [
        "Оригинальная дорожка"
      ],
      "quality": "dvdrip",
      "translation": "Оригинальная дорожка",
      "update": "2020-11-03 12:57:13",
      "iframe_src": ""
    },
    {
      "id": 6520,
      "title": "Чудеса жизни",
      "kp_id": "760592",
      "imdb_id": "tt2699374",
      "world_art_id": null,
      "type": "serial",
      "add": "2020-01-30 20:37:05",
      "orig_title": "Wonders of Life",
      "year": "2013-01-27",
      "translations": [
        "Профессиональный (одноголосый закадровый)"
      ],
      "seasons_count": 1,
      "episodes_count": 5,
      "episodes": 5,
      "update": "2020-01-31 13:39:49",
      "iframe_src": ""
    },
    {
      "id": 6519,
      "title": "Чистильщик",
      "kp_id": "400630",
      "imdb_id": "tt1103973",
      "world_art_id": null,
      "type": "serial",
      "add": "2020-01-30 20:29:49",
      "orig_title": "The Cleaner",
      "year": "2008-07-15",
      "translations": [
        "Профессиональный (многоголосый закадровый) (Fox Crime)"
      ],
      "seasons_count": 2,
      "episodes_count": 26,
      "episodes": 13,
      "update": "2020-01-31 13:26:03",
      "iframe_src": ""
    },
    {
      "id": 6518,
      "title": "Соседи",
      "kp_id": "663135",
      "imdb_id": "tt2182229",
      "world_art_id": null,
      "type": "serial",
      "add": "2020-01-30 13:39:36",
      "orig_title": "The Neighbors",
      "year": "2012-09-26",
      "translations": [
        "Профессиональный (многоголосый закадровый) (FOX)"
      ],
      "seasons_count": 2,
      "episodes_count": 44,
      "episodes": 22,
      "update": "2020-01-31 13:12:47",
      "iframe_src": ""
    },
    {
      "id": 6517,
      "title": "Соседи из ада",
      "kp_id": "496862",
      "imdb_id": "tt1592270",
      "world_art_id": null,
      "type": "serial",
      "add": "2020-01-30 13:36:26",
      "orig_title": "Neighbors from Hell",
      "year": "2010-06-07",
      "translations": [
        "Профессиональный (многоголосый закадровый) (2x2)"
      ],
      "seasons_count": 1,
      "episodes_count": 10,
      "episodes": 10,
      "update": "2020-01-30 21:41:26",
      "iframe_src": ""
    },
    {
      "id": 6515,
      "title": "Живые и мертвые",
      "kp_id": "45336",
      "imdb_id": "tt0057717",
      "world_art_id": null,
      "type": "serial",
      "add": "2020-01-30 13:03:30",
      "orig_title": "Zhivye i myortvye",
      "year": "1964-02-18",
      "translations": [
        "Оригинальная дорожка"
      ],
      "seasons_count": 1,
      "episodes_count": 2,
      "episodes": 2,
      "update": "2020-01-30 21:31:51",
      "iframe_src": ""
    },
    {
      "id": 6513,
      "title": "Истории, леденящие кровь",
      "kp_id": "584390",
      "imdb_id": "tt0442648",
      "world_art_id": null,
      "type": "serial",
      "add": "2020-01-30 09:18:20",
      "orig_title": "Twisted Tales",
      "year": "2005-01-16",
      "translations": [
        "Профессиональный (двухголосый закадровый)"
      ],
      "seasons_count": 1,
      "episodes_count": 14,
      "episodes": 14,
      "update": "2020-01-30 19:24:36",
      "iframe_src": ""
    },
    {
      "id": 6512,
      "title": "Клиент всегда мертв",
      "kp_id": "181807",
      "imdb_id": "tt0248654",
      "world_art_id": null,
      "type": "serial",
      "add": "2020-01-30 08:31:10",
      "orig_title": "Six Feet Under",
      "year": "2001-06-03",
      "translations": [
        "Профессиональный (многоголосый закадровый) (NovaFilm)",
        "Профессиональный (одноголосый закадровый)",
        "Авторский (одноголосый закадровый) (Сербин Юрий)"
      ],
      "seasons_count": 5,
      "episodes_count": 63,
      "episodes": 12,
      "update": "2020-01-30 19:43:33",
      "iframe_src": ""
    },
    {
      "id": 6511,
      "title": "Гимнастки",
      "kp_id": "433849",
      "imdb_id": "tt1332030",
      "world_art_id": null,
      "type": "serial",
      "add": "2020-01-30 08:10:58",
      "orig_title": "Make It or Break It",
      "year": "2009-06-22",
      "translations": [
        "Профессиональный (многоголосый закадровый) (MTV)"
      ],
      "seasons_count": 3,
      "episodes_count": 47,
      "episodes": 8,
      "update": "2020-01-30 19:05:13",
      "iframe_src": ""
    },
    {
      "id": 6510,
      "title": "Жёны заключенных",
      "kp_id": "679664",
      "imdb_id": "tt2188249",
      "world_art_id": null,
      "type": "serial",
      "add": "2020-01-29 22:47:31",
      "orig_title": "Prisoners Wives",
      "year": "2012-01-31",
      "translations": [
        "Профессиональный (многоголосый закадровый) (BaibaKo)"
      ],
      "seasons_count": 1,
      "episodes_count": 6,
      "episodes": 6,
      "update": "2020-01-30 21:35:36",
      "iframe_src": ""
    },
    {
      "id": 6508,
      "title": "Обитель тьмы Гарта Маренги",
      "kp_id": "471995",
      "imdb_id": "tt0397150",
      "world_art_id": null,
      "type": "serial",
      "add": "2020-01-29 20:54:39",
      "orig_title": "Garth Marenghi's Darkplace",
      "year": "2004-01-29",
      "translations": [
        "Профессиональный (многоголосый закадровый) (Ozz.tv)"
      ],
      "seasons_count": 1,
      "episodes_count": 6,
      "episodes": 6,
      "update": "2020-01-30 21:30:31",
      "iframe_src": ""
    },
    {
      "id": 6507,
      "title": "Всё сначала",
      "kp_id": "839218",
      "imdb_id": "tt3572034",
      "world_art_id": null,
      "type": "serial",
      "add": "2020-01-29 15:51:35",
      "orig_title": "Vsyo snachala",
      "year": "2014-01-01",
      "translations": [
        "Оригинальная дорожка"
      ],
      "seasons_count": 1,
      "episodes_count": 4,
      "episodes": 4,
      "update": "2020-01-30 14:07:34",
      "iframe_src": ""
    },
    {
      "id": 6506,
      "title": "Мария Верн",
      "kp_id": "679551",
      "imdb_id": "tt1129398",
      "world_art_id": null,
      "type": "serial",
      "add": "2020-01-29 15:13:52",
      "orig_title": "Maria Wern",
      "year": "2008-09-16",
      "translations": [
        "Профессиональный (многоголосый закадровый) (Русский репортаж)"
      ],
      "seasons_count": 4,
      "episodes_count": 13,
      "episodes": 2,
      "update": "2020-01-30 14:04:27",
      "iframe_src": ""
    },
    {
      "id": 6487,
      "title": "Робин Гуд",
      "kp_id": "399155",
      "imdb_id": "tt0787985",
      "world_art_id": null,
      "type": "serial",
      "add": "2020-01-28 05:36:24",
      "orig_title": "Robin Hood",
      "year": "2006-10-07",
      "translations": [
        "Профессиональный (многоголосый закадровый) (ТВ3)"
      ],
      "seasons_count": 3,
      "episodes_count": 39,
      "episodes": 13,
      "update": "2020-01-30 07:40:16",
      "iframe_src": ""
    },
    {
      "id": 6451,
      "title": "Мужская работа 2",
      "kp_id": "409131",
      "imdb_id": "tt4744344",
      "world_art_id": null,
      "type": "serial",
      "add": "2020-01-23 09:08:31",
      "orig_title": "Muzhskaya rabota 2",
      "year": "2002-01-01",
      "translations": [
        "Оригинальная дорожка"
      ],
      "seasons_count": 1,
      "episodes_count": 10,
      "episodes": 10,
      "update": "2020-01-30 22:41:51",
      "iframe_src": ""
    },
    {
      "id": 6450,
      "title": "Мужская работа",
      "kp_id": "409130",
      "imdb_id": "tt4623456",
      "world_art_id": null,
      "type": "serial",
      "add": "2020-01-23 08:57:33",
      "orig_title": "Muzhskaya rabota",
      "year": "2001-01-01",
      "translations": [
        "Оригинальная дорожка"
      ],
      "seasons_count": 1,
      "episodes_count": 8,
      "episodes": 8,
      "update": "2020-01-30 22:07:57",
      "iframe_src": ""
    },
    {
      "id": 6446,
      "title": "Перекресток смерти",
      "kp_id": "542549",
      "imdb_id": "tt1697033",
      "world_art_id": null,
      "type": "serial",
      "add": "2020-01-22 21:18:29",
      "orig_title": "True Justice",
      "year": "2010-12-27",
      "translations": [
        "Полное дублирование (РенТВ)"
      ],
      "seasons_count": 1,
      "episodes_count": 13,
      "episodes": 13,
      "update": "2020-01-30 17:49:33",
      "iframe_src": ""
    },
    {
      "id": 6444,
      "title": "Зоя",
      "kp_id": "481499",
      "imdb_id": null,
      "world_art_id": null,
      "type": "serial",
      "add": "2020-01-22 17:53:05",
      "orig_title": "Зоя",
      "year": "2010-11-01",
      "translations": [
        "Оригинальная дорожка"
      ],
      "seasons_count": 1,
      "episodes_count": 8,
      "episodes": 8,
      "update": "2020-01-30 21:47:38",
      "iframe_src": ""
    },
    {
      "id": 6417,
      "title": "Ученица Мессинга",
      "kp_id": "1007523",
      "imdb_id": null,
      "world_art_id": null,
      "type": "serial",
      "add": "2020-01-20 18:36:38",
      "orig_title": "Ученица Мессинга",
      "year": "2020-01-20",
      "translations": [
        "Оригинальная дорожка"
      ],
      "seasons_count": 1,
      "episodes_count": 16,
      "episodes": 16,
      "update": "2020-01-30 23:23:01",
      "iframe_src": ""
    },
    {
      "id": 6187,
      "title": "Суд над Кристиной Килер",
      "kp_id": "1190060",
      "imdb_id": "tt8001036",
      "world_art_id": null,
      "type": "serial",
      "add": "2019-12-30 13:03:17",
      "orig_title": "The Trial of Christine Keeler",
      "year": "2019-12-29",
      "translations": [
        "Любительский (многоголосый закадровый) (Octopus)",
        "Профессиональный (многоголосый закадровый) (TVShows)"
      ],
      "seasons_count": 1,
      "episodes_count": 6,
      "episodes": 6,
      "update": "2020-01-30 23:22:40",
      "iframe_src": ""
    },
    {
      "id": 6145,
      "title": "Место, что домом зовётся",
      "kp_id": "807534",
      "imdb_id": "tt2258904",
      "world_art_id": null,
      "type": "serial",
      "add": "2019-12-26 09:12:54",
      "orig_title": "A Place to Call Home",
      "year": "2013-04-28",
      "translations": [
        "Любительский (многоголосый закадровый)",
        "Любительский (двухголосый закадровый)",
        "Любительский (многоголосый закадровый) (GreenРай Studio)"
      ],
      "seasons_count": 3,
      "episodes_count": 27,
      "episodes": 10,
      "update": "2020-01-30 11:21:57",
      "iframe_src": ""
    },
    {
      "id": 30109,
      "title": "Ужасные истории: Древние римляне",
      "kp_id": "1194466",
      "imdb_id": "tt7715070",
      "world_art_id": null,
      "type": "movie",
      "add": "2019-08-19 07:32:40",
      "orig_title": "Horrible Histories: The Movie - Rotten Romans",
      "year": "2019-07-26",
      "translations": [
        "Любительский (многоголосый закадровый) (AlphaProject)",
        "Original (English)",
        "Полное дублирование (iTunes)"
      ],
      "quality": "webdl",
      "translation": "Любительский (многоголосый закадровый) (AlphaProject)",
      "update": "2020-11-03 16:06:35",
      "iframe_src": ""
    },
    {
      "id": 13711,
      "title": "Кролик и бык",
      "kp_id": "421734",
      "imdb_id": "tt1251725",
      "world_art_id": null,
      "type": "movie",
      "add": "2017-10-04 07:41:19",
      "orig_title": "Bunny and the Bull",
      "year": "2009-09-16",
      "translations": [
        "Профессиональный (двухголосый закадровый)",
        "Original (English)",
        "Профессиональный (двухголосый закадровый)"
      ],
      "quality": "hdrip",
      "translation": "Профессиональный (двухголосый закадровый)",
      "update": "2020-11-03 16:05:07",
      "iframe_src": ""
    }
  ]
}
